semantics/__init__.py
semantics/pipeline.py
semantics/train.py
semantics/classifiers/__init__.py
semantics/classifiers/resnet.py
semantics/vision/__init__.py
semantics/vision/channels.py
semantics/vision/decoder.py
semantics/vision/encoder.py
semantics/vision/metrics.py
semantics/vision/models/__init__.py
semantics/vision/models/swinjscc.py
semantics/vision/models/vscc.py
semantics/vision/models/witt.py
semantics_pytorch-0.4.0.dist-info/METADATA
semantics_pytorch-0.4.0.dist-info/WHEEL
semantics_pytorch-0.4.0.dist-info/top_level.txt
semantics_pytorch-0.4.0.dist-info/RECORD
