Metadata-Version: 2.4
Name: semantics-pytorch
Version: 0.4.0
Summary: Utilities for implementing semantic communication workflows in PyTorch
Author: Jordan Madden
Requires-Dist: numpy==2.3.2
Requires-Dist: pillow==11.3.0
Requires-Dist: pytorch-msssim==1.0.0
Requires-Dist: timm==1.0.19
Requires-Dist: torch==2.8.0
Requires-Dist: torchvision==0.23.0
Requires-Dist: tqdm==4.67.1
Dynamic: author
Dynamic: requires-dist
Dynamic: summary
